README.rst
setup.cfg
setup.py
postman_client/__init__.py
postman_client/client.py
postman_client/exceptions.py
postman_client/models.py
postman_client/test_variables.py
postman_client/tests.py
postman_client.egg-info/PKG-INFO
postman_client.egg-info/SOURCES.txt
postman_client.egg-info/dependency_links.txt
postman_client.egg-info/requires.txt
postman_client.egg-info/top_level.txt