Metadata-Version: 1.1
Name: postman-client
Version: 0.1.11
Summary: Client service, to send simple text emails or, using a template created at Postman, send more complex emails.
Home-page: https://github.com/ThCC/postman-client
Author: Thiago Cardoso de Castro
Author-email: thiago.decastro2@gmail.com
License: MIT
Platform: UNKNOWN
Classifier: Environment :: Web Environment
Classifier: Intended Audience :: Developers
Classifier: License :: OSI Approved :: MIT License
Classifier: Operating System :: OS Independent
Classifier: Programming Language :: Python
Classifier: Programming Language :: Python :: 2
Classifier: Topic :: Software Development :: Libraries
